<frames><frame number="0" /><frame number="1"><bbox><x>104</x><y>535</y><width>175</width><height>384</height><occlusion>0</occlusion></bbox></frame><frame number="2"><bbox><x>97</x><y>543</y><width>173</width><height>305</height><occlusion>0</occlusion></bbox><bbox><x>101</x><y>543</y><width>170</width><height>358</height><occlusion>0</occlusion></bbox></frame><frame number="3"><bbox><x>97</x><y>535</y><width>156</width><height>388</height><occlusion>0</occlusion></bbox></frame><frame number="4"><bbox><x>46</x><y>538</y><width>175</width><height>373</height><occlusion>0</occlusion></bbox><bbox><x>90</x><y>534</y><width>160</width><height>386</height><occlusion>0</occlusion></bbox></frame><frame number="5"><bbox><x>51</x><y>529</y><width>161</width><height>388</height><occlusion>0</occlusion></bbox><bbox><x>86</x><y>515</y><width>154</width><height>412</height><occlusion>0</occlusion></bbox></frame><frame number="6"><bbox><x>42</x><y>492</y><width>171</width><height>403</height><occlusion>0</occlusion></bbox><bbox><x>45</x><y>515</y><width>169</width><height>416</height><occlusion>0</occlusion></bbox><bbox><x>2</x><y>612</y><width>93</width><height>314</height><occlusion>0</occlusion></bbox></frame><frame number="7"><bbox><x>24</x><y>470</y><width>175</width><height>441</height><occlusion>0</occlusion></bbox><bbox><x>26</x><y>493</y><width>177</width><height>453</height><occlusion>0</occlusion></bbox></frame><frame number="8" /><frame number="9"><bbox><x>5</x><y>461</y><width>162</width><height>461</height><occlusion>0</occlusion></bbox><bbox><x>8</x><y>492</y><width>162</width><height>449</height><occlusion>0</occlusion></bbox><bbox><x>452</x><y>726</y><width>93</width><height>161</height><occlusion>0</occlusion></bbox><bbox><x>462</x><y>757</y><width>69</width><height>125</height><occlusion>0</occlusion></bbox></frame><frame number="10"><bbox><x>7</x><y>451</y><width>156</width><height>473</height><occlusion>0</occlusion></bbox></frame><frame number="11" /><frame number="12"><bbox><x>426</x><y>738</y><width>88</width><height>151</height><occlusion>0</occlusion></bbox></frame><frame number="13" /><frame number="14" /><frame number="15" /><frame number="16" /><frame number="17" /><frame number="18" /><frame number="19" /><frame number="20" /><frame number="21" /><frame number="22" /><frame number="23" /><frame number="24" /><frame number="25" /><frame number="26" /><frame number="27" /><frame number="28" /><frame number="29" /><frame number="30" /><frame number="31" /><frame number="32" /><frame number="33"><bbox><x>505</x><y>769</y><width>64</width><height>136</height><occlusion>0</occlusion></bbox></frame><frame number="34"><bbox><x>501</x><y>750</y><width>63</width><height>155</height><occlusion>0</occlusion></bbox><bbox><x>496</x><y>771</y><width>69</width><height>128</height><occlusion>0</occlusion></bbox></frame><frame number="35" /><frame number="36" /><frame number="37" /><frame number="38" /><frame number="39" /><frame number="40"><bbox><x>434</x><y>721</y><width>81</width><height>185</height><occlusion>0</occlusion></bbox></frame><frame number="41" /><frame number="42" /><frame number="43"><bbox><x>406</x><y>711</y><width>89</width><height>202</height><occlusion>0</occlusion></bbox></frame><frame number="44"><bbox><x>391</x><y>710</y><width>93</width><height>213</height><occlusion>0</occlusion></bbox><bbox><x>404</x><y>719</y><width>87</width><height>201</height><occlusion>0</occlusion></bbox></frame><frame number="45"><bbox><x>382</x><y>710</y><width>96</width><height>215</height><occlusion>0</occlusion></bbox></frame><frame number="46"><bbox><x>365</x><y>702</y><width>97</width><height>226</height><occlusion>0</occlusion></bbox></frame><frame number="47" /><frame number="48"><bbox><x>346</x><y>688</y><width>82</width><height>249</height><occlusion>0</occlusion></bbox></frame><frame number="49"><bbox><x>316</x><y>681</y><width>97</width><height>252</height><occlusion>0</occlusion></bbox><bbox><x>331</x><y>686</y><width>90</width><height>248</height><occlusion>0</occlusion></bbox></frame><frame number="50" /><frame number="51" /><frame number="52" /><frame number="53" /><frame number="54" /><frame number="55" /><frame number="56" /><frame number="57" /><frame number="58" /><frame number="59" /><frame number="60" /><frame number="61" /><frame number="62" /><frame number="63" /><frame number="64" /><frame number="65" /><frame number="66" /><frame number="67" /><frame number="68" /><frame number="69" /><frame number="70" /><frame number="71" /><frame number="72" /><frame number="73" /><frame number="74" /><frame number="75" /><frame number="76" /><frame number="77" /><frame number="78" /><frame number="79" /><frame number="80" /><frame number="81" /><frame number="82" /><frame number="83" /><frame number="84" /><frame number="85" /><frame number="86" /><frame number="87" /><frame number="88" /><frame number="89" /><frame number="90" /><frame number="91" /><frame number="92" /><frame number="93" /><frame number="94" /><frame number="95" /><frame number="96" /><frame number="97" /><frame number="98" /><frame number="99" /><frame number="100" /><frame number="101" /><frame number="102" /><frame number="103" /><frame number="104" /><frame number="105" /><frame number="106" /><frame number="107" /><frame number="108" /><frame number="109" /><frame number="110" /><frame number="111" /><frame number="112" /></frames>